DestinyNet/__init__.py
DestinyNet/train.py
DestinyNet/utils.py
destinynet-0.1.2.dist-info/METADATA
destinynet-0.1.2.dist-info/WHEEL
destinynet-0.1.2.dist-info/RECORD
